LICENSE
MANIFEST.in
README.rst
marrie.py
setup.py
marrie.egg-info/PKG-INFO
marrie.egg-info/SOURCES.txt
marrie.egg-info/dependency_links.txt
marrie.egg-info/entry_points.txt
marrie.egg-info/requires.txt
marrie.egg-info/top_level.txt