Metadata-Version: 1.1
Name: marrie
Version: 0.3.1
Summary: A simple podcast client that runs on the Command Line Interface.
Home-page: http://projects.rafaelmartins.eng.br/marrie/
Author: Rafael Goncalves Martins
Author-email: rafael@rafaelmartins.eng.br
License: BSD
Platform: UNKNOWN
Classifier: Development Status :: 3 - Alpha
Classifier: Environment :: Console
Classifier: License :: OSI Approved :: BSD License
Classifier: Operating System :: OS Independent
Classifier: Programming Language :: Python :: 2.7
Classifier: Topic :: Multimedia :: Sound/Audio
Classifier: Topic :: Multimedia :: Video
